chrpa_test/__init__.py
chrpa_test/main/__init__.py
chrpa_test/main/processing.py
chrpa_test/tests/__init__.py
chrpa_test/tests/test_chrpa_test.py
chrpa_test-0.0.1.dist-info/METADATA
chrpa_test-0.0.1.dist-info/WHEEL
chrpa_test-0.0.1.dist-info/licenses/LICENSE
chrpa_test-0.0.1.dist-info/RECORD
