Metadata-Version: 2.1
Name: chrpa_test
Version: 0.0.1
Summary: A github test
Author-email: HM & GP <hmendo@sandia.gov>
License-File: LICENSE
Classifier: License :: OSI Approved :: MIT License
Classifier: Operating System :: OS Independent
Classifier: Programming Language :: Python :: 3
Requires-Python: >=3.10
